Topsis_Saksham_102003673/__init__.py
Topsis_Saksham_102003673-0.0.7.dist-info/LICENSE.txt
Topsis_Saksham_102003673-0.0.7.dist-info/METADATA
Topsis_Saksham_102003673-0.0.7.dist-info/WHEEL
Topsis_Saksham_102003673-0.0.7.dist-info/top_level.txt
Topsis_Saksham_102003673-0.0.7.dist-info/RECORD
