Metadata-Version: 2.1
Name: Topsis-Saksham-102003673
Version: 0.0.7
Summary: A package -> Calculates Topsis Score and Ranks them accordingly
Author: Saksham Yadav
Author-email: syadav1_be20@thapar.edu
Classifier: Programming Language :: Python :: 3
Classifier: License :: OSI Approved :: MIT License
Classifier: Operating System :: OS Independent
License-File: LICENSE.txt
Requires-Dist: pandas
Requires-Dist: numpy
